capyc/__about__.py
capyc/__init__.py
capyc/admin.py
capyc/apps.py
capyc/models.py
capyc/receivers.py
capyc/settings.py
capyc/core/__init__.py
capyc/core/i18n.py
capyc/core/managers.py
capyc/core/object.py
capyc/core/shorteners.py
capyc/django/__init__.py
capyc/django/admin.py
capyc/django/cache.py
capyc/django/models.py
capyc/django/receivers.py
capyc/django/serializer.py
capyc/django/tasks.py
capyc/django/utils.py
capyc/management/__init__.py
capyc/management/commands/__init__.py
capyc/management/commands/clean_cache.py
capyc/management/commands/deploy_cache.py
capyc/migrations/__init__.py
capyc/pytest/__init__.py
capyc/pytest/circuitbreaker/__init__.py
capyc/pytest/circuitbreaker/fixtures/__init__.py
capyc/pytest/circuitbreaker/fixtures/dont_close_the_circuit.py
capyc/pytest/core/__init__.py
capyc/pytest/core/fixtures/__init__.py
capyc/pytest/core/fixtures/clean_cache.py
capyc/pytest/core/fixtures/clean_environment.py
capyc/pytest/core/fixtures/fake.py
capyc/pytest/core/fixtures/format.py
capyc/pytest/core/fixtures/image.py
capyc/pytest/core/fixtures/no_http_requests.py
capyc/pytest/core/fixtures/random.py
capyc/pytest/core/fixtures/seed.py
capyc/pytest/django/__init__.py
capyc/pytest/django/fixtures/__init__.py
capyc/pytest/django/fixtures/database.py
capyc/pytest/django/fixtures/datetime.py
capyc/pytest/django/fixtures/queryset.py
capyc/pytest/django/fixtures/signals.py
capyc/pytest/django/fixtures/utils/__init__.py
capyc/pytest/django/fixtures/utils/argument_parser.py
capyc/pytest/newrelic/__init__.py
capyc/pytest/newrelic/fixtures/__init__.py
capyc/pytest/newrelic/fixtures/disable_new_relic.py
capyc/pytest/newrelic/fixtures/disable_newrelic_prints.py
capyc/pytest/rest_framework/__init__.py
capyc/pytest/rest_framework/fixtures/__init__.py
capyc/pytest/rest_framework/fixtures/client.py
capyc/rest_framework/__init__.py
capyc/rest_framework/exception_handler.py
capyc/rest_framework/exceptions.py
capyc/rest_framework/urls.py
capyc/rest_framework/views.py
capy_core-1.3.1.dist-info/METADATA
capy_core-1.3.1.dist-info/WHEEL
capy_core-1.3.1.dist-info/licenses/LICENSE.txt
capy_core-1.3.1.dist-info/RECORD
