Metadata-Version: 2.3
Name: capy-core
Version: 1.3.1
Project-URL: Documentation, https://breatheco-de.github.io/capy-core/
Project-URL: Issues, https://github.com/breatheco-de/capy-core/issues
Project-URL: Source, https://github.com/breatheco-de/capy-core
Author-email: jefer94 <jdefreitaspinto@gmail.com>
License: MIT
Classifier: Development Status :: 5 - Production/Stable
Classifier: Framework :: Django :: 4.2
Classifier: Framework :: Django :: 5.0
Classifier: License :: OSI Approved :: MIT License
Classifier: Programming Language :: Python
Classifier: Programming Language :: Python :: 3.10
Classifier: Programming Language :: Python :: 3.11
Classifier: Programming Language :: Python :: 3.12
Classifier: Programming Language :: Python :: Implementation :: CPython
Classifier: Programming Language :: Python :: Implementation :: PyPy
Classifier: Topic :: Software Development :: Libraries
Requires-Python: >=3.11
Requires-Dist: langcodes
Provides-Extra: celery
Requires-Dist: celery; extra == 'celery'
Provides-Extra: django
Requires-Dist: adrf; extra == 'django'
Requires-Dist: brotli; extra == 'django'
Requires-Dist: circuitbreaker; extra == 'django'
Requires-Dist: django; extra == 'django'
Requires-Dist: django-redis; extra == 'django'
Requires-Dist: djangorestframework; extra == 'django'
Requires-Dist: zstandard; extra == 'django'
Provides-Extra: pytest
Requires-Dist: numpy; extra == 'pytest'
Requires-Dist: pillow; extra == 'pytest'
Requires-Dist: pytz; extra == 'pytest'
